README.md
setup.cfg
setup.py
misp_stix_converter/__init__.py
misp_stix_converter/errors.py
misp_stix_converter/misp-to-stix.py
misp_stix_converter/stix-to-misp.py
misp_stix_converter.egg-info/PKG-INFO
misp_stix_converter.egg-info/SOURCES.txt
misp_stix_converter.egg-info/dependency_links.txt
misp_stix_converter.egg-info/requires.txt
misp_stix_converter.egg-info/top_level.txt
misp_stix_converter/converters/__init__.py
misp_stix_converter/converters/buildMISPAttribute.py
misp_stix_converter/converters/buildSTIXAttribute.py
misp_stix_converter/converters/convert.py
misp_stix_converter/converters/lint_roller.py
misp_stix_converter/servers/__init__.py
misp_stix_converter/servers/misp.py