Metadata-Version: 1.0
Name: misp-stix-converter
Version: 0.2.11
Summary: A tool to convert between STIX and MISP format
Home-page: https://github.com/FloatingGhost/MISP-STIX-Converter
Author: Hannah Ward
Author-email: hannah.ward@baesystems.com
License: UNKNOWN
Platform: UNKNOWN
